vigileguard/__init__.py
vigileguard/container_security_checkers.py
vigileguard/database_security_checkers.py
vigileguard/enhanced_reporting.py
vigileguard/environment_security_checkers.py
vigileguard/phase2_integration.py
vigileguard/process_security_checkers.py
vigileguard/vigileguard.py
vigileguard/web_security_checkers.py
vigileguard-3.0.6.dist-info/licenses/LICENSE
vigileguard-3.0.6.dist-info/METADATA
vigileguard-3.0.6.dist-info/WHEEL
vigileguard-3.0.6.dist-info/entry_points.txt
vigileguard-3.0.6.dist-info/top_level.txt
vigileguard-3.0.6.dist-info/RECORD
