Metadata-Version: 2.4
Name: vigileguard
Version: 3.0.6
Summary: Comprehensive Linux Security Audit Tool with Phase 1 & 2 Features
Home-page: https://github.com/navinnm/VigileGuard
Author: VigileGuard Team
Author-email: VigileGuard Development Team <security@vigileguard.dev>
Maintainer-email: VigileGuard Development Team <security@vigileguard.dev>
License: MIT
Project-URL: Homepage, https://github.com/navinnm/VigileGuard
Project-URL: Documentation, https://github.com/navinnm/VigileGuard/blob/main/docs/
Project-URL: Repository, https://github.com/navinnm/VigileGuard
Project-URL: Bug Tracker, https://github.com/navinnm/VigileGuard/issues
Project-URL: Changelog, https://github.com/navinnm/VigileGuard/blob/main/CHANGELOG.md
Keywords: security,audit,linux,compliance,vulnerability,scanning,assessment,hardening,monitoring,reporting
Platform: Linux
Platform: Unix
Classifier: Development Status :: 4 - Beta
Classifier: Environment :: Console
Classifier: Intended Audience :: System Administrators
Classifier: Intended Audience :: Information Technology
Classifier: License :: OSI Approved :: MIT License
Classifier: Operating System :: POSIX :: Linux
Classifier: Programming Language :: Python :: 3
Classifier: Programming Language :: Python :: 3.8
Classifier: Programming Language :: Python :: 3.9
Classifier: Programming Language :: Python :: 3.10
Classifier: Programming Language :: Python :: 3.11
Classifier: Programming Language :: Python :: 3.12
Classifier: Topic :: Security
Classifier: Topic :: System :: Systems Administration
Classifier: Topic :: System :: Monitoring
Classifier: Topic :: System :: Networking :: Monitoring
Requires-Python: >=3.8
License-File: LICENSE
Requires-Dist: click>=8.1.7
Requires-Dist: rich>=13.7.0
Requires-Dist: PyYAML>=6.0.1
Requires-Dist: requests>=2.25.0
Provides-Extra: dev
Requires-Dist: pytest>=6.0; extra == "dev"
Requires-Dist: pytest-cov>=2.0; extra == "dev"
Requires-Dist: black>=21.0; extra == "dev"
Requires-Dist: flake8>=3.8; extra == "dev"
Requires-Dist: mypy>=0.800; extra == "dev"
Requires-Dist: bandit>=1.7; extra == "dev"
Requires-Dist: safety>=1.10; extra == "dev"
Provides-Extra: notifications
Requires-Dist: requests>=2.25.0; extra == "notifications"
Provides-Extra: full
Requires-Dist: requests>=2.25.0; extra == "full"
Requires-Dist: pytest>=6.0; extra == "full"
Requires-Dist: pytest-cov>=2.0; extra == "full"
Dynamic: author
Dynamic: home-page
Dynamic: license-file
Dynamic: platform
Dynamic: requires-python
